dotstrap/__init__.py
dotstrap/dotstrap.py
dotstrap-0.1.9.dist-info/entry_points.txt
dotstrap-0.1.9.dist-info/WHEEL
dotstrap-0.1.9.dist-info/METADATA
dotstrap-0.1.9.dist-info/RECORD
