Metadata-Version: 2.1
Name: dotstrap
Version: 0.1.9
Summary: A simiple Python based command line tool that acts as a git wrapper for simplifying dotfile management via bare git repository.
Author: mark
Author-email: mark@dixon.se
Requires-Python: >=3.8,<4.0
Classifier: Programming Language :: Python :: 3
Classifier: Programming Language :: Python :: 3.8
Classifier: Programming Language :: Python :: 3.9
Requires-Dist: click (>=8.0.1,<9.0.0)
Requires-Dist: pexpect (>=4.8.0,<5.0.0)
